README.md
setup.py
UP_Tree.egg-info/PKG-INFO
UP_Tree.egg-info/SOURCES.txt
UP_Tree.egg-info/dependency_links.txt
UP_Tree.egg-info/top_level.txt
src/UPTree.py
src/__init__.py