Metadata-Version: 2.1
Name: UP-Tree
Version: 0.0.3
Summary: This is a simple module which takes input of transactions and provides it's UP-Tree, HeaderTable, and transactions dictionary
Home-page: https://github.com/miths/UPTree
Author: Mithil Ghinaiya
Author-email: mghinaiya@gmail.com
License: UNKNOWN
Platform: UNKNOWN
Classifier: Programming Language :: Python :: 3
Classifier: License :: OSI Approved :: MIT License
Classifier: Operating System :: OS Independent
Requires-Python: >=3.6
